CHANGES.txt
LICENCE.txt
MANIFEST.in
README.md
setup.py
pygameoflife/GUI.py
pygameoflife/__init__.py
pygameoflife/model.py
pygameoflife.egg-info/PKG-INFO
pygameoflife.egg-info/SOURCES.txt
pygameoflife.egg-info/dependency_links.txt
pygameoflife.egg-info/entry_points.txt
pygameoflife.egg-info/requires.txt
pygameoflife.egg-info/top_level.txt